redis_dec/CacheDecorator.py
redis_dec/__init__.py
redis_decorator-0.4.dist-info/METADATA
redis_decorator-0.4.dist-info/RECORD
redis_decorator-0.4.dist-info/WHEEL
redis_decorator-0.4.dist-info/top_level.txt
tests/__init__.py
tests/cache_test.py
