Metadata-Version: 2.1
Name: redis-decorator
Version: 0.4
Summary: Using redis as external redis_dec by one line of code
Home-page: https://github.com/louisLouL/louisPy
Author: Louis Lou
Author-email: qijia.lou@nyu.edu
License: UNKNOWN
Platform: UNKNOWN
Classifier: Programming Language :: Python :: 3
Classifier: License :: OSI Approved :: MIT License
Classifier: Operating System :: OS Independent
